{
    "/js/app.js": "/js/app.js?id=1381d4cf6df44dcf7441",
    "/css/app.css": "/css/app.css?id=5c9a19e4c7d6ae0790d9",
    "/css/auth.css": "/css/auth.css?id=452a002710d80b3af4cb",
    "/js/app.js.map": "/js/app.js.map?id=476aec36805620e7c9bd",
    "/css/app.css.map": "/css/app.css.map?id=2f08613e10a1f9b5e383",
    "/css/auth.css.map": "/css/auth.css.map?id=15b67aad97faa5b1a985",
    "/js/vendor.js": "/js/vendor.js?id=1dd22d0981d6330a3046",
    "/js/vendor.js.map": "/js/vendor.js.map?id=c2643acf7bea1d3247b7",
    "/js/manifest.js": "/js/manifest.js?id=d64713044d4b02b1808b",
    "/js/manifest.js.map": "/js/manifest.js.map?id=f6e84b4aa949d0a8c97b"
}
